LICENSE
MANIFEST.in
README.md
setup.cfg
setup.py
zephyr/__init__.py
zephyr/backend/__init__.py
zephyr/backend/analytical.py
zephyr/backend/base.py
zephyr/backend/discretization.py
zephyr/backend/distributors.py
zephyr/backend/eurus.py
zephyr/backend/interpolation.py
zephyr/backend/minizephyr.py
zephyr/backend/source.py
zephyr/backend/Tests/__init__.py
zephyr/backend/Tests/test_Analytical.py
zephyr/backend/Tests/test_Eurus.py
zephyr/backend/Tests/test_MiniZephyr.py
zephyr/backend/Tests/test_Sources.py
zephyr/frontend/__init__.py
zephyr/frontend/cli.py
zephyr/frontend/jobs.py
zephyr/middleware/__init__.py
zephyr/middleware/db.py
zephyr/middleware/fields.py
zephyr/middleware/maps.py
zephyr/middleware/optimization.py
zephyr/middleware/problem.py
zephyr/middleware/regularization.py
zephyr/middleware/survey.py
zephyr/middleware/time.py
zephyr/middleware/util.py
zephyr/middleware/Tests/__init__.py
zephyr_seis.egg-info/PKG-INFO
zephyr_seis.egg-info/SOURCES.txt
zephyr_seis.egg-info/dependency_links.txt
zephyr_seis.egg-info/entry_points.txt
zephyr_seis.egg-info/pbr.json
zephyr_seis.egg-info/requires.txt
zephyr_seis.egg-info/top_level.txt