Metadata-Version: 1.1
Name: zephyr-seis
Version: 0.1.3
Summary: zephyr
Home-page: UNKNOWN
Author: Brendan Smithyman
Author-email: brendan@bitsmithy.net
License: MIT
Download-URL: http://github.com/uwoseis/zephyr
Keywords: full-waveform inversion
Platform: Windows
Platform: Linux
Platform: Solaris
Platform: Mac OS-X
Platform: Unix
Classifier: Development Status :: 3 - Alpha
Classifier: Intended Audience :: Developers
Classifier: Intended Audience :: Science/Research
Classifier: License :: OSI Approved :: MIT License
Classifier: Programming Language :: Python
Classifier: Topic :: Scientific/Engineering
Classifier: Topic :: Scientific/Engineering :: Mathematics
Classifier: Topic :: Scientific/Engineering :: Physics
Classifier: Operating System :: Microsoft :: Windows
Classifier: Operating System :: POSIX
Classifier: Operating System :: Unix
Classifier: Operating System :: MacOS
Classifier: Natural Language :: English
